LICENSE.md
census2020/__init__.py
census2020/cli.py
census2020/constants.py
census2020/downloader.py
census2020/parsers.py
census2020/readers.py
census2020/types.py
census2020-0.1.0.dist-info/entry_points.txt
census2020-0.1.0.dist-info/LICENSE.md
census2020-0.1.0.dist-info/WHEEL
census2020-0.1.0.dist-info/METADATA
census2020-0.1.0.dist-info/RECORD
