Metadata-Version: 2.1
Name: census2020
Version: 0.1.0
Summary: Some helper functions for working with Census 2020 data
Home-page: https://github.com/khwilson/Census2020
License: MIT
Keywords: census,pl94,decennial,redistricting
Author: Kevin Wilson
Author-email: khwilson@gmail.com
Requires-Python: >=3.7.1,<4.0.0
Classifier: Development Status :: 3 - Alpha
Classifier: Intended Audience :: Developers
Classifier: Intended Audience :: Science/Research
Classifier: License :: OSI Approved :: MIT License
Classifier: Natural Language :: English
Classifier: Operating System :: OS Independent
Classifier: Programming Language :: Python :: 3
Classifier: Programming Language :: Python :: 3.10
Classifier: Programming Language :: Python :: 3.7
Classifier: Programming Language :: Python :: 3.8
Classifier: Programming Language :: Python :: 3.9
Requires-Dist: StrEnum (>=0.4.6,<0.5.0)
Requires-Dist: click (>=8.0.1,<9.0.0)
Requires-Dist: pyarrow (>=5.0.0,<6.0.0)
Requires-Dist: requests (>=2.26.0,<3.0.0)
Requires-Dist: tqdm (>=4.62.1,<5.0.0)
Requires-Dist: us (>=2.0.2,<3.0.0)
Project-URL: Repository, https://github.com/khwilson/Census2020
